{"guide_ad-hoc.md":"e434a8ee","readme.md":"aa660219","guide_command-color-types.md":"a48fb3c7","guide_index.md":"bdbe68d5","guide_install.md":"6fec355f","guide_intro-inventory.md":"4b10b5a1","guide_playbook.md":"ddf75dfc","index.md":"742bee32","module_apt.md":"d93ad86c","module_archive.md":"6e69fd29","module_command.md":"27f2a127","module_copy.md":"be5c2f97","module_cron.md":"335e0786","module_fetch.md":"6ee475db","module_group.md":"e9268789","module_hostname.md":"a7680bf4","module_lineinfile.md":"4f515658","module_index.md":"7d6d247e","module_replace.md":"3549de64","module_service.md":"8cc74b83","module_script.md":"ecae4660","module_package.md":"f95daaa0","module_user.md":"2bc3d878","module_setup.md":"ab0ef390","module_ping.md":"2fc9a839","module_shell.md":"127a7bc9","module_systemd.md":"f3c9e68d","module_unarchive.md":"0b0470e3","guide_verification-method.md":"e769f3b3","module_file.md":"401e29c3","module_yum.md":"f0012f53"}
